bads/__init__.py
bads/h0rn3t.py
bads-0.1.0.dist-info/licenses/LICENSE
bads-0.1.0.dist-info/METADATA
bads-0.1.0.dist-info/WHEEL
bads-0.1.0.dist-info/top_level.txt
bads-0.1.0.dist-info/RECORD
