Metadata-Version: 2.4
Name: bads
Version: 0.1.0
Summary: BADS Community: A simple threaded path scanner
Author: H0rn3t Sp1d3rs
License: MIT License
Requires-Python: >=3.6
License-File: LICENSE
Requires-Dist: requests
Requires-Dist: colorama
Dynamic: license-file
